{
    "index": 23877,
    "tags": [
        {
            "name": "index",
            "value": 23877
        },
        {
            "name": "hexID",
            "value": ""
        },
        {
            "name": "oompType",
            "value": "FOOTPRINT"
        },
        {
            "name": "oompSize",
            "value": "kicad"
        },
        {
            "name": "oompColor",
            "value": "kicad-footprints"
        },
        {
            "name": "oompDesc",
            "value": "Package_DFN_QFN"
        },
        {
            "name": "oompIndex",
            "value": "VQFN-64-1EP_9x9mm_P0.5mm_EP5.4x5.4mm"
        },
        {
            "name": "oompName",
            "value": "kicad-footprints/Package_DFN_QFN/VQFN-64-1EP_9x9mm_P0.5mm_EP5.4x5.4mm"
        },
        {
            "name": "kicadDesc",
            "value": "VQFN, 64 Pin (http://ww1.microchip.com/downloads/en/DeviceDoc/PIC16LF19195-6-7-Data-Sheet-40001873D.pdf#page=718), generated with kicad-footprint-generator ipc_noLead_generator.py"
        },
        {
            "name": "kicadTags",
            "value": "VQFN NoLead"
        },
        {
            "name": "kicadAttr",
            "value": "smd"
        },
        {
            "name": "kicad3DModel",
            "value": "${KICAD6_3DMODEL_DIR}/Package_DFN_QFN.3dshapes/VQFN-64-1EP_9x9mm_P0.5mm_EP5.4x5.4mm.wrl"
        },
        {
            "name": "oompID",
            "value": "FOOTPRINT-kicad-kicad-footprints-Package_DFN_QFN-VQFN-64-1EP_9x9mm_P0.5mm_EP5.4x5.4mm"
        },
        {
            "name": "name",
            "value": ""
        }
    ]
}