
<package name="USB-A-S-SILK-FEMALE">
<description>&lt;h3&gt;USB Type 'A' Female Connector - SMT Silk Outline&lt;/h3&gt;
Shield pins may be grounded.
&lt;br&gt; tDocu shows plug end. 
&lt;p&gt;Specifications:
&lt;ul&gt;&lt;li&gt;Pin count:6&lt;/li&gt;
&lt;/ul&gt;&lt;/p&gt;
&lt;p&gt;&lt;a href=” https://www.sparkfun.com/datasheets/Prototyping/Connectors/USBFemaleTypeA.pdf”&gt;Datasheet referenced for footprint&lt;/a&gt;&lt;/p&gt;
&lt;p&gt;Example device(s):
&lt;ul&gt;&lt;li&gt;USB_A&lt;/li&gt;
&lt;/ul&gt;&lt;/p&gt;</description>
<wire x1="6.6957" y1="6.5659" x2="-7.287" y2="6.5659" width="0.127" layer="51"/>
<wire x1="6.6957" y1="-6.5659" x2="-7.287" y2="-6.5659" width="0.127" layer="51"/>
<wire x1="-7.287" y1="6.477" x2="-7.287" y2="-6.477" width="0.127" layer="51"/>
<wire x1="6.7084" y1="6.5024" x2="6.7084" y2="-6.5024" width="0.127" layer="51"/>
<wire x1="0.46" y1="-5.08" x2="-5.89" y2="-4.445" width="0.127" layer="51"/>
<wire x1="-5.89" y1="-4.445" x2="-5.89" y2="-1.27" width="0.127" layer="51"/>
<wire x1="-5.89" y1="-1.27" x2="0.46" y2="-0.635" width="0.127" layer="51"/>
<wire x1="0.46" y1="5.08" x2="-5.89" y2="4.445" width="0.127" layer="51"/>
<wire x1="-5.89" y1="4.445" x2="-5.89" y2="1.27" width="0.127" layer="51"/>
<wire x1="-5.89" y1="1.27" x2="0.46" y2="0.635" width="0.127" layer="51"/>
<wire x1="-7.366" y1="6.604" x2="0.508" y2="6.604" width="0.2032" layer="21"/>
<wire x1="-7.366" y1="6.604" x2="-7.366" y2="-6.604" width="0.2032" layer="21"/>
<wire x1="-7.366" y1="-6.604" x2="0.508" y2="-6.604" width="0.2032" layer="21"/>
<wire x1="5.08" y1="-6.604" x2="6.858" y2="-6.604" width="0.2032" layer="21"/>
<wire x1="6.858" y1="-6.604" x2="6.858" y2="-4.318" width="0.2032" layer="21"/>
<wire x1="6.858" y1="4.318" x2="6.858" y2="6.604" width="0.2032" layer="21"/>
<wire x1="6.858" y1="6.604" x2="5.08" y2="6.604" width="0.2032" layer="21"/>
<pad name="SHLD1" x="3" y="-6.5659" drill="2.3114" rot="R270"/>
<pad name="SHLD2" x="3" y="6.5659" drill="2.3114" rot="R270"/>
<smd name="D-" x="7.212" y="1" dx="3" dy="0.9" layer="1"/>
<smd name="VBUS" x="7.212" y="3.5" dx="3" dy="0.9" layer="1"/>
<smd name="D+" x="7.212" y="-1" dx="3" dy="0.9" layer="1"/>
<smd name="GND" x="7.212" y="-3.5" dx="3" dy="0.9" layer="1"/>
<text x="-6.35" y="6.858" size="0.6096" layer="25" font="vector" ratio="20">&gt;NAME</text>
<text x="-6.35" y="-6.858" size="0.6096" layer="27" font="vector" ratio="20" align="top-left">&gt;VALUE</text>
</package>
