{
    "index": 11175,
    "tags": [
        {
            "name": "index",
            "value": 11175
        },
        {
            "name": "hexID",
            "value": ""
        },
        {
            "name": "oompType",
            "value": "FOOTPRINT"
        },
        {
            "name": "oompSize",
            "value": "kicad"
        },
        {
            "name": "oompColor",
            "value": "kicad-footprints"
        },
        {
            "name": "oompDesc",
            "value": "RF_Mini-Circuits"
        },
        {
            "name": "oompIndex",
            "value": "Mini-Circuits_CD542_LandPatternPL-052"
        },
        {
            "name": "oompName",
            "value": "kicad-footprints/RF_Mini-Circuits/Mini-Circuits_CD542_LandPatternPL-052"
        },
        {
            "name": "kicadDesc",
            "value": "Footprint for Mini-Circuits case CD542 (https://ww2.minicircuits.com/case_style/CD542.pdf) using land-pattern PL-052, including GND-vias (https://ww2.minicircuits.com/pcb/98-pl052.pdf)"
        },
        {
            "name": "kicadTags",
            "value": "MiniCircuits PL-052 CD542"
        },
        {
            "name": "kicadAttr",
            "value": "smd"
        },
        {
            "name": "kicad3DModel",
            "value": "${KICAD6_3DMODEL_DIR}/RF_Mini-Circuits.3dshapes/Mini-Circuits_CD542.wrl"
        },
        {
            "name": "oompID",
            "value": "FOOTPRINT-kicad-kicad-footprints-RF_Mini-Circuits-Mini-Circuits_CD542_LandPatternPL-052"
        },
        {
            "name": "name",
            "value": ""
        }
    ]
}