{
    "index": 40374,
    "tags": [
        {
            "name": "index",
            "value": 40374
        },
        {
            "name": "hexID",
            "value": ""
        },
        {
            "name": "oompType",
            "value": "FOOTPRINT"
        },
        {
            "name": "oompSize",
            "value": "eagle"
        },
        {
            "name": "oompColor",
            "value": "eagle-default"
        },
        {
            "name": "oompDesc",
            "value": "switch-misc"
        },
        {
            "name": "oompIndex",
            "value": "RF15L2"
        },
        {
            "name": "oompName",
            "value": "eagle-default/switch-misc/RF15L2"
        },
        {
            "name": "oompID",
            "value": "FOOTPRINT-eagle-eagle-default-switch-misc-RF15L2"
        },
        {
            "name": "name",
            "value": ""
        }
    ]
}