{
    "index": 39529,
    "tags": [
        {
            "name": "index",
            "value": 39529
        },
        {
            "name": "hexID",
            "value": ""
        },
        {
            "name": "oompType",
            "value": "FOOTPRINT"
        },
        {
            "name": "oompSize",
            "value": "eagle"
        },
        {
            "name": "oompColor",
            "value": "eagle-default"
        },
        {
            "name": "oompDesc",
            "value": "resistor-power"
        },
        {
            "name": "oompIndex",
            "value": "RS02C_17-23"
        },
        {
            "name": "oompName",
            "value": "eagle-default/resistor-power/RS02C_17-23"
        },
        {
            "name": "oompID",
            "value": "FOOTPRINT-eagle-eagle-default-resistor-power-RS02C_17-23"
        },
        {
            "name": "name",
            "value": ""
        }
    ]
}