{
    "index": 15250,
    "tags": [
        {
            "name": "index",
            "value": 15250
        },
        {
            "name": "hexID",
            "value": ""
        },
        {
            "name": "oompType",
            "value": "FOOTPRINT"
        },
        {
            "name": "oompSize",
            "value": "kicad"
        },
        {
            "name": "oompColor",
            "value": "kicad-footprints"
        },
        {
            "name": "oompDesc",
            "value": "Connector"
        },
        {
            "name": "oompIndex",
            "value": "FanPinHeader_1x04_P2.54mm_Vertical"
        },
        {
            "name": "oompName",
            "value": "kicad-footprints/Connector/FanPinHeader_1x04_P2.54mm_Vertical"
        },
        {
            "name": "kicadDesc",
            "value": "4-pin CPU fan Through hole pin header, e.g. for Wieson part number 2366C888-007 Molex 47053-1000, Foxconn HF27040-M1, Tyco 1470947-1 or equivalent, see http://www.formfactors.org/developer%5Cspecs%5Crev1_2_public.pdf"
        },
        {
            "name": "kicadTags",
            "value": "pin header 4-pin CPU fan"
        },
        {
            "name": "kicadAttr",
            "value": "through_hole"
        },
        {
            "name": "kicad3DModel",
            "value": "${KICAD6_3DMODEL_DIR}/Connector.3dshapes/FanPinHeader_1x04_P2.54mm_Vertical.wrl"
        },
        {
            "name": "oompID",
            "value": "FOOTPRINT-kicad-kicad-footprints-Connector-FanPinHeader_1x04_P2.54mm_Vertical"
        },
        {
            "name": "name",
            "value": ""
        }
    ]
}