{
    "tags": [
        {
            "name": "hexID",
            "value": ""
        },
        {
            "name": "oompType",
            "value": "FOOTPRINT"
        },
        {
            "name": "oompSize",
            "value": "eagle"
        },
        {
            "name": "oompColor",
            "value": "SparkFun-Eagle-Libraries"
        },
        {
            "name": "oompDesc",
            "value": "Sparkfun-Connectors"
        },
        {
            "name": "oompIndex",
            "value": "BTA"
        },
        {
            "name": "oompName",
            "value": "SparkFun-Eagle-Libraries/Sparkfun-Connectors/BTA"
        },
        {
            "name": "description",
            "value": "&lt;h3&gt;British Telecom Connector - Analog Right Angle&lt;/h3&gt;\n&lt;p&gt;Specifications:\n&lt;ul&gt;&lt;li&gt;Pin count: 6&lt;/li&gt;\n&lt;/ul&gt;&lt;/p&gt;\n&lt;p&gt;&lt;a href=http://cdn.sparkfun.com/datasheets/Prototyping/BTA-Connector%20Datasheet.pdf&gt;Datasheet referenced for footprint&lt;/a&gt;&lt;/p&gt;\n&lt;p&gt;Example device(s):\n&lt;ul&gt;&lt;li&gt;VERNIER_ANALOG&lt;/li&gt;\n&lt;/ul&gt;&lt;/p&gt;"
        },
        {
            "name": "oompID",
            "value": "FOOTPRINT-eagle-SparkFun-Eagle-Libraries-Sparkfun-Connectors-BTA"
        },
        {
            "name": "name",
            "value": ""
        }
    ]
}