{
    "tags": [
        {
            "name": "hexID",
            "value": ""
        },
        {
            "name": "oompType",
            "value": "FOOTPRINT"
        },
        {
            "name": "oompSize",
            "value": "kicad"
        },
        {
            "name": "oompColor",
            "value": "kicad-footprints"
        },
        {
            "name": "oompDesc",
            "value": "Transformer_SMD"
        },
        {
            "name": "oompIndex",
            "value": "Transformer_Murata_78250JC"
        },
        {
            "name": "oompName",
            "value": "kicad-footprints/Transformer_SMD/Transformer_Murata_78250JC"
        },
        {
            "name": "kicadDesc",
            "value": "Murata 78250JC https://www.murata-ps.com/datasheet?/data/magnetics/kmp_78250j.pdf"
        },
        {
            "name": "kicadTags",
            "value": "Murata transformer"
        },
        {
            "name": "kicadAttr",
            "value": "smd"
        },
        {
            "name": "kicad3DModel",
            "value": "${KICAD6_3DMODEL_DIR}/Transformer_SMD.3dshapes/Transformer_Murata_78250JC.wrl"
        },
        {
            "name": "oompID",
            "value": "FOOTPRINT-kicad-kicad-footprints-Transformer_SMD-Transformer_Murata_78250JC"
        },
        {
            "name": "name",
            "value": ""
        }
    ]
}