<package name="JST-PH-2-SMT-RA">
<description>2-Pin JST PH Series Right-Angle Connector (+/- for batteries)</description>
<wire x1="-4" y1="3" x2="4" y2="3" width="0.2032" layer="51"/>
<wire x1="4" y1="3" x2="4" y2="-4.5" width="0.2032" layer="51"/>
<wire x1="-4" y1="-4.5" x2="-4" y2="3" width="0.2032" layer="51"/>
<wire x1="3.2" y1="-2" x2="-3.2" y2="-2" width="0.2032" layer="51"/>
<wire x1="-3.2" y1="-2" x2="-3.2" y2="-4.5" width="0.2032" layer="51"/>
<wire x1="-3.2" y1="-4.5" x2="-4" y2="-4.5" width="0.2032" layer="51"/>
<wire x1="4" y1="-4.5" x2="3.2" y2="-4.5" width="0.2032" layer="51"/>
<wire x1="3.2" y1="-4.5" x2="3.2" y2="-2" width="0.2032" layer="51"/>
<wire x1="-2.25" y1="3" x2="2.25" y2="3" width="0.127" layer="21"/>
<wire x1="4" y1="-0.5" x2="4" y2="-4.5" width="0.127" layer="21"/>
<wire x1="4" y1="-4.5" x2="3.15" y2="-4.5" width="0.127" layer="21"/>
<wire x1="3.15" y1="-4.5" x2="3.15" y2="-2" width="0.127" layer="21"/>
<wire x1="3.15" y1="-2" x2="1.75" y2="-2" width="0.127" layer="21"/>
<wire x1="-1.75" y1="-2" x2="-3.15" y2="-2" width="0.127" layer="21"/>
<wire x1="-3.15" y1="-2" x2="-3.15" y2="-4.5" width="0.127" layer="21"/>
<wire x1="-3.15" y1="-4.5" x2="-4" y2="-4.5" width="0.127" layer="21"/>
<wire x1="-4" y1="-4.5" x2="-4" y2="-0.5" width="0.127" layer="21"/>
<smd name="2" x="-1" y="-3.7" dx="1" dy="4.6" layer="1"/>
<smd name="1" x="1" y="-3.7" dx="1" dy="4.6" layer="1"/>
<smd name="NC1" x="-3.4" y="1.5" dx="3.4" dy="1.6" layer="1" rot="R90"/>
<smd name="NC2" x="3.4" y="1.5" dx="3.4" dy="1.6" layer="1" rot="R90"/>
<text x="-2.54" y="3.81" size="1.27" layer="25" font="vector">&gt;Name</text>
<text x="-2.54" y="-7.62" size="1.27" layer="27" font="vector">&gt;Value</text>
<text x="2.286" y="-6.096" size="1.4224" layer="21" ratio="12">+</text>
<text x="-3.429" y="-6.096" size="1.4224" layer="21" ratio="12">-</text>
</package>
