{
    "index": 8334,
    "tags": [
        {
            "name": "index",
            "value": 8334
        },
        {
            "name": "hexID",
            "value": ""
        },
        {
            "name": "oompType",
            "value": "FOOTPRINT"
        },
        {
            "name": "oompSize",
            "value": "kicad"
        },
        {
            "name": "oompColor",
            "value": "kicad-footprints"
        },
        {
            "name": "oompDesc",
            "value": "MountingHole"
        },
        {
            "name": "oompIndex",
            "value": "MountingHole_3.2mm_M3_Pad"
        },
        {
            "name": "oompName",
            "value": "kicad-footprints/MountingHole/MountingHole_3.2mm_M3_Pad"
        },
        {
            "name": "kicadDesc",
            "value": "Mounting Hole 3.2mm, M3"
        },
        {
            "name": "kicadTags",
            "value": "mounting hole 3.2mm m3"
        },
        {
            "name": "kicadAttr",
            "value": "exclude_from_pos_files exclude_from_bom"
        },
        {
            "name": "oompID",
            "value": "FOOTPRINT-kicad-kicad-footprints-MountingHole-MountingHole_3.2mm_M3_Pad"
        },
        {
            "name": "name",
            "value": ""
        }
    ]
}