<package name="PLCC20" urn="urn:adsk.eagle:footprint:8083656/1">
<description>&lt;b&gt;Plastic Leaded Chip Carrier&lt;/b&gt;</description>
<wire x1="-4.7" y1="4.7" x2="4.3" y2="4.7" width="0.1524" layer="51"/>
<wire x1="4.3" y1="4.7" x2="4.7" y2="4.3" width="0.1524" layer="51"/>
<wire x1="4.7" y1="4.3" x2="4.7" y2="-4.3" width="0.1524" layer="51"/>
<wire x1="4.7" y1="-4.3" x2="4.3" y2="-4.7" width="0.1524" layer="51"/>
<wire x1="4.3" y1="-4.7" x2="-3.7" y2="-4.7" width="0.1524" layer="51"/>
<wire x1="4.2" y1="4" x2="4.2" y2="-4" width="0.0508" layer="51"/>
<wire x1="4.2" y1="-4" x2="4" y2="-4.2" width="0.0508" layer="51"/>
<wire x1="4" y1="-4.2" x2="-3.7" y2="-4.2" width="0.0508" layer="51"/>
<wire x1="-3.7" y1="-4.2" x2="-3.7" y2="4.2" width="0.0508" layer="51"/>
<wire x1="-3.7" y1="4.2" x2="4" y2="4.2" width="0.0508" layer="51"/>
<wire x1="4" y1="4.2" x2="4.2" y2="4" width="0.0508" layer="51"/>
<wire x1="-4.7" y1="-3.2" x2="-4.7" y2="4.7" width="0.1524" layer="51"/>
<wire x1="-4.7" y1="-3.2" x2="-3.7" y2="-4.2" width="0.0508" layer="51"/>
<wire x1="-3.7" y1="-4.7" x2="-4.7" y2="-3.2" width="0.1524" layer="51"/>
<wire x1="-4.45" y1="0.25" x2="-3.95" y2="0.25" width="0.0508" layer="51" curve="-180"/>
<wire x1="-4.45" y1="-0.25" x2="-3.95" y2="-0.25" width="0.0508" layer="51" curve="180"/>
<wire x1="-3.95" y1="0.25" x2="-3.95" y2="-0.25" width="0.0508" layer="51"/>
<wire x1="-4.45" y1="0.25" x2="-4.45" y2="-0.25" width="0.0508" layer="51"/>
<wire x1="4.3" y1="4.7" x2="4" y2="4.2" width="0.0508" layer="51"/>
<wire x1="4.2" y1="4" x2="4.7" y2="4.3" width="0.0508" layer="51"/>
<wire x1="4.2" y1="-4" x2="4.7" y2="-4.3" width="0.0508" layer="51"/>
<wire x1="4" y1="-4.2" x2="4.3" y2="-4.7" width="0.0508" layer="51"/>
<wire x1="-2.049" y1="4.7" x2="-1.761" y2="4.7" width="0.1524" layer="21"/>
<wire x1="-0.779" y1="4.7" x2="-0.491" y2="4.7" width="0.1524" layer="21"/>
<wire x1="0.491" y1="4.7" x2="0.779" y2="4.7" width="0.1524" layer="21"/>
<wire x1="1.761" y1="4.7" x2="2.049" y2="4.7" width="0.1524" layer="21"/>
<wire x1="3.031" y1="4.7" x2="4.3" y2="4.7" width="0.1524" layer="21"/>
<wire x1="4.3" y1="4.7" x2="4.7" y2="4.3" width="0.1524" layer="21"/>
<wire x1="4.7" y1="4.3" x2="4.7" y2="3.031" width="0.1524" layer="21"/>
<wire x1="4.7" y1="2.049" x2="4.7" y2="1.761" width="0.1524" layer="21"/>
<wire x1="4.7" y1="0.779" x2="4.7" y2="0.491" width="0.1524" layer="21"/>
<wire x1="4.7" y1="-0.491" x2="4.7" y2="-0.779" width="0.1524" layer="21"/>
<wire x1="4.7" y1="-1.761" x2="4.7" y2="-2.049" width="0.1524" layer="21"/>
<wire x1="4.7" y1="-3.031" x2="4.7" y2="-4.3" width="0.1524" layer="21"/>
<wire x1="4.7" y1="-4.3" x2="4.3" y2="-4.7" width="0.1524" layer="21"/>
<wire x1="4.3" y1="-4.7" x2="3.031" y2="-4.7" width="0.1524" layer="21"/>
<wire x1="2.049" y1="-4.7" x2="1.761" y2="-4.7" width="0.1524" layer="21"/>
<wire x1="0.779" y1="-4.7" x2="0.491" y2="-4.7" width="0.1524" layer="21"/>
<wire x1="-0.491" y1="-4.7" x2="-0.779" y2="-4.7" width="0.1524" layer="21"/>
<wire x1="-1.761" y1="-4.7" x2="-2.049" y2="-4.7" width="0.1524" layer="21"/>
<wire x1="-3.031" y1="-4.7" x2="-3.7" y2="-4.7" width="0.1524" layer="21"/>
<wire x1="-3.7" y1="-4.7" x2="-4.7" y2="-3.21" width="0.1524" layer="21"/>
<wire x1="-4.7" y1="-3.21" x2="-4.7" y2="-3.031" width="0.1524" layer="21"/>
<wire x1="-4.7" y1="-2.049" x2="-4.7" y2="-1.761" width="0.1524" layer="21"/>
<wire x1="-4.7" y1="-0.779" x2="-4.7" y2="-0.491" width="0.1524" layer="21"/>
<wire x1="-4.7" y1="0.491" x2="-4.7" y2="0.779" width="0.1524" layer="21"/>
<wire x1="-4.7" y1="1.761" x2="-4.7" y2="2.049" width="0.1524" layer="21"/>
<wire x1="-4.7" y1="3.031" x2="-4.7" y2="4.7" width="0.1524" layer="21"/>
<wire x1="-4.7" y1="4.7" x2="-3.031" y2="4.7" width="0.1524" layer="21"/>
<wire x1="-3.7" y1="4.2" x2="-2.991" y2="4.2" width="0.0508" layer="21"/>
<wire x1="-2.089" y1="4.2" x2="-1.721" y2="4.2" width="0.0508" layer="21"/>
<wire x1="-0.819" y1="4.2" x2="-0.451" y2="4.2" width="0.0508" layer="21"/>
<wire x1="0.451" y1="4.2" x2="0.819" y2="4.2" width="0.0508" layer="21"/>
<wire x1="1.721" y1="4.2" x2="2.089" y2="4.2" width="0.0508" layer="21"/>
<wire x1="2.991" y1="4.2" x2="4" y2="4.2" width="0.0508" layer="21"/>
<wire x1="4" y1="4.2" x2="4.2" y2="4" width="0.0508" layer="21"/>
<wire x1="4.2" y1="4" x2="4.2" y2="2.991" width="0.0508" layer="21"/>
<wire x1="4.2" y1="2.089" x2="4.2" y2="1.721" width="0.0508" layer="21"/>
<wire x1="4.2" y1="0.819" x2="4.2" y2="0.451" width="0.0508" layer="21"/>
<wire x1="4.2" y1="-0.451" x2="4.2" y2="-0.819" width="0.0508" layer="21"/>
<wire x1="4.2" y1="-1.721" x2="4.2" y2="-2.089" width="0.0508" layer="21"/>
<wire x1="4.2" y1="-2.991" x2="4.2" y2="-4" width="0.0508" layer="21"/>
<wire x1="4.2" y1="-4" x2="4" y2="-4.2" width="0.0508" layer="21"/>
<wire x1="4" y1="-4.2" x2="2.991" y2="-4.2" width="0.0508" layer="21"/>
<wire x1="2.089" y1="-4.2" x2="1.721" y2="-4.2" width="0.0508" layer="21"/>
<wire x1="0.819" y1="-4.2" x2="0.451" y2="-4.2" width="0.0508" layer="21"/>
<wire x1="-0.451" y1="-4.2" x2="-0.819" y2="-4.2" width="0.0508" layer="21"/>
<wire x1="-1.721" y1="-4.2" x2="-2.089" y2="-4.2" width="0.0508" layer="21"/>
<wire x1="-2.991" y1="-4.2" x2="-3.7" y2="-4.2" width="0.0508" layer="21"/>
<wire x1="-3.7" y1="-4.2" x2="-4.69" y2="-3.21" width="0.0508" layer="21"/>
<wire x1="-3.7" y1="-2.089" x2="-3.7" y2="-1.721" width="0.0508" layer="21"/>
<wire x1="-3.7" y1="-0.819" x2="-3.7" y2="-0.451" width="0.0508" layer="21"/>
<wire x1="-3.7" y1="0.451" x2="-3.7" y2="0.819" width="0.0508" layer="21"/>
<wire x1="-3.7" y1="1.721" x2="-3.7" y2="2.089" width="0.0508" layer="21"/>
<wire x1="-3.7" y1="2.991" x2="-3.7" y2="4.2" width="0.0508" layer="21"/>
<wire x1="-4.7" y1="4.7" x2="-3.7" y2="4.2" width="0.0508" layer="51"/>
<wire x1="4.3" y1="4.7" x2="4" y2="4.2" width="0.0508" layer="21"/>
<wire x1="4.2" y1="4" x2="4.7" y2="4.3" width="0.0508" layer="21"/>
<wire x1="4.2" y1="-4" x2="4.7" y2="-4.3" width="0.0508" layer="21"/>
<wire x1="4" y1="-4.2" x2="4.3" y2="-4.7" width="0.0508" layer="21"/>
<wire x1="-4.7" y1="4.7" x2="-3.7" y2="4.2" width="0.0508" layer="21"/>
<wire x1="-3.7" y1="-4.2" x2="-3.7" y2="-2.991" width="0.0508" layer="21"/>
<wire x1="-3.7" y1="-4.2" x2="-3.7" y2="-4.69" width="0.0508" layer="21"/>
<smd name="4" x="-2.54" y="-4.05" dx="0.76" dy="1.8" layer="1"/>
<smd name="5" x="-1.27" y="-4.05" dx="0.76" dy="1.8" layer="1"/>
<smd name="6" x="0" y="-4.05" dx="0.76" dy="1.8" layer="1"/>
<smd name="7" x="1.27" y="-4.05" dx="0.76" dy="1.8" layer="1"/>
<smd name="8" x="2.54" y="-4.05" dx="0.76" dy="1.8" layer="1"/>
<smd name="18" x="-2.54" y="4.05" dx="0.76" dy="1.8" layer="1"/>
<smd name="17" x="-1.27" y="4.05" dx="0.76" dy="1.8" layer="1"/>
<smd name="16" x="0" y="4.05" dx="0.76" dy="1.8" layer="1"/>
<smd name="15" x="1.27" y="4.05" dx="0.76" dy="1.8" layer="1"/>
<smd name="14" x="2.54" y="4.05" dx="0.76" dy="1.8" layer="1"/>
<smd name="13" x="4.05" y="2.54" dx="1.8" dy="0.76" layer="1"/>
<smd name="12" x="4.05" y="1.27" dx="1.8" dy="0.76" layer="1"/>
<smd name="11" x="4.05" y="0" dx="1.8" dy="0.76" layer="1"/>
<smd name="10" x="4.05" y="-1.27" dx="1.8" dy="0.76" layer="1"/>
<smd name="9" x="4.05" y="-2.54" dx="1.8" dy="0.76" layer="1"/>
<smd name="3" x="-4.05" y="-2.54" dx="1.8" dy="0.76" layer="1"/>
<smd name="2" x="-4.05" y="-1.27" dx="1.8" dy="0.76" layer="1"/>
<smd name="1" x="-4.05" y="0" dx="1.8" dy="0.76" layer="1"/>
<smd name="20" x="-4.05" y="1.27" dx="1.8" dy="0.76" layer="1"/>
<smd name="19" x="-4.05" y="2.54" dx="1.8" dy="0.76" layer="1"/>
<text x="-3.048" y="-6.858" size="1.27" layer="27" ratio="10">&gt;VALUE</text>
<text x="-3.175" y="5.715" size="1.27" layer="25" ratio="10">&gt;NAME</text>
<rectangle x1="-2.79" y1="-4.95" x2="-2.29" y2="-4.7" layer="51"/>
<rectangle x1="-2.79" y1="4.7" x2="-2.29" y2="4.95" layer="51"/>
<rectangle x1="-1.52" y1="4.7" x2="-1.02" y2="4.95" layer="51"/>
<rectangle x1="-0.25" y1="4.7" x2="0.25" y2="4.95" layer="51"/>
<rectangle x1="1.02" y1="4.7" x2="1.52" y2="4.95" layer="51"/>
<rectangle x1="2.29" y1="4.7" x2="2.79" y2="4.95" layer="51"/>
<rectangle x1="1.02" y1="4.7" x2="1.52" y2="4.95" layer="51"/>
<rectangle x1="-0.25" y1="4.7" x2="0.25" y2="4.95" layer="51"/>
<rectangle x1="4.7" y1="2.29" x2="4.95" y2="2.79" layer="51"/>
<rectangle x1="4.7" y1="1.02" x2="4.95" y2="1.52" layer="51"/>
<rectangle x1="4.7" y1="-0.25" x2="4.95" y2="0.25" layer="51"/>
<rectangle x1="4.7" y1="-1.52" x2="4.95" y2="-1.02" layer="51"/>
<rectangle x1="4.7" y1="-2.79" x2="4.95" y2="-2.29" layer="51"/>
<rectangle x1="-1.52" y1="-4.95" x2="-1.02" y2="-4.7" layer="51"/>
<rectangle x1="-0.25" y1="-4.95" x2="0.25" y2="-4.7" layer="51"/>
<rectangle x1="1.02" y1="-4.95" x2="1.52" y2="-4.7" layer="51"/>
<rectangle x1="2.29" y1="-4.95" x2="2.79" y2="-4.7" layer="51"/>
<rectangle x1="-4.95" y1="2.29" x2="-4.7" y2="2.79" layer="51"/>
<rectangle x1="-4.95" y1="1.02" x2="-4.7" y2="1.52" layer="51"/>
<rectangle x1="-4.95" y1="-0.25" x2="-4.7" y2="0.25" layer="51"/>
<rectangle x1="-4.95" y1="-1.52" x2="-4.7" y2="-1.02" layer="51"/>
<rectangle x1="-4.95" y1="-2.79" x2="-4.7" y2="-2.29" layer="51"/>
</package>
