{
    "index": 8846,
    "tags": [
        {
            "name": "index",
            "value": 8846
        },
        {
            "name": "hexID",
            "value": ""
        },
        {
            "name": "oompType",
            "value": "FOOTPRINT"
        },
        {
            "name": "oompSize",
            "value": "eagle"
        },
        {
            "name": "oompColor",
            "value": "eagle-default"
        },
        {
            "name": "oompDesc",
            "value": "ref-packages"
        },
        {
            "name": "oompIndex",
            "value": "RTRIMTS63Z"
        },
        {
            "name": "oompName",
            "value": "eagle-default/ref-packages/RTRIMTS63Z"
        },
        {
            "name": "oompID",
            "value": "FOOTPRINT-eagle-eagle-default-ref-packages-RTRIMTS63Z"
        },
        {
            "name": "name",
            "value": ""
        }
    ]
}