{
    "index": 39876,
    "tags": [
        {
            "name": "index",
            "value": 39876
        },
        {
            "name": "hexID",
            "value": ""
        },
        {
            "name": "oompType",
            "value": "FOOTPRINT"
        },
        {
            "name": "oompSize",
            "value": "eagle"
        },
        {
            "name": "oompColor",
            "value": "eagle-default"
        },
        {
            "name": "oompDesc",
            "value": "smd-ipc"
        },
        {
            "name": "oompIndex",
            "value": "SQFP-S-14X14-108"
        },
        {
            "name": "oompName",
            "value": "eagle-default/smd-ipc/SQFP-S-14X14-108"
        },
        {
            "name": "oompID",
            "value": "FOOTPRINT-eagle-eagle-default-smd-ipc-SQFP-S-14X14-108"
        },
        {
            "name": "name",
            "value": ""
        }
    ]
}