{
    "tags": [
        {
            "name": "hexID",
            "value": ""
        },
        {
            "name": "oompType",
            "value": "FOOTPRINT"
        },
        {
            "name": "oompSize",
            "value": "kicad"
        },
        {
            "name": "oompColor",
            "value": "kicad-footprints"
        },
        {
            "name": "oompDesc",
            "value": "Converter_ACDC"
        },
        {
            "name": "oompIndex",
            "value": "Converter_ACDC_RECOM_RAC04-xxSGx_THT"
        },
        {
            "name": "oompName",
            "value": "kicad-footprints/Converter_ACDC/Converter_ACDC_RECOM_RAC04-xxSGx_THT"
        },
        {
            "name": "kicadDesc",
            "value": "https://www.recom-power.com/pdf/Powerline-AC-DC/RAC04-GA.pdf"
        },
        {
            "name": "kicadTags",
            "value": "recom power ac dc"
        },
        {
            "name": "kicadAttr",
            "value": "through_hole"
        },
        {
            "name": "kicad3DModel",
            "value": "${KICAD6_3DMODEL_DIR}/Converter_ACDC.3dshapes/Converter_ACDC_RECOM_RAC04-xxSGx_THT.wrl"
        },
        {
            "name": "oompID",
            "value": "FOOTPRINT-kicad-kicad-footprints-Converter_ACDC-Converter_ACDC_RECOM_RAC04-xxSGx_THT"
        },
        {
            "name": "name",
            "value": ""
        }
    ]
}