{
    "index": 35413,
    "tags": [
        {
            "name": "index",
            "value": 35413
        },
        {
            "name": "hexID",
            "value": ""
        },
        {
            "name": "oompType",
            "value": "FOOTPRINT"
        },
        {
            "name": "oompSize",
            "value": "eagle"
        },
        {
            "name": "oompColor",
            "value": "eagle-default"
        },
        {
            "name": "oompDesc",
            "value": "rcl"
        },
        {
            "name": "oompIndex",
            "value": "SANYO-OSCON_SMD_B6"
        },
        {
            "name": "oompName",
            "value": "eagle-default/rcl/SANYO-OSCON_SMD_B6"
        },
        {
            "name": "oompID",
            "value": "FOOTPRINT-eagle-eagle-default-rcl-SANYO-OSCON_SMD_B6"
        },
        {
            "name": "name",
            "value": ""
        }
    ]
}