{
    "tags": [
        {
            "name": "hexID",
            "value": ""
        },
        {
            "name": "oompType",
            "value": "FOOTPRINT"
        },
        {
            "name": "oompSize",
            "value": "kicad"
        },
        {
            "name": "oompColor",
            "value": "kicad-footprints"
        },
        {
            "name": "oompDesc",
            "value": "Package_SO"
        },
        {
            "name": "oompIndex",
            "value": "SO-4_4.4x2.3mm_P1.27mm"
        },
        {
            "name": "oompName",
            "value": "kicad-footprints/Package_SO/SO-4_4.4x2.3mm_P1.27mm"
        },
        {
            "name": "kicadDesc",
            "value": "4-Lead Plastic Small Outline (SO), see http://datasheet.octopart.com/OPIA403BTRE-Optek-datasheet-5328560.pdf"
        },
        {
            "name": "kicadTags",
            "value": "SO SOIC 1.27"
        },
        {
            "name": "kicadAttr",
            "value": "smd"
        },
        {
            "name": "kicad3DModel",
            "value": "${KICAD6_3DMODEL_DIR}/Package_SO.3dshapes/SO-4_4.4x2.3mm_P1.27mm.wrl"
        },
        {
            "name": "oompID",
            "value": "FOOTPRINT-kicad-kicad-footprints-Package_SO-SO-4_4.4x2.3mm_P1.27mm"
        },
        {
            "name": "name",
            "value": ""
        }
    ]
}