{
    "index": 8142,
    "tags": [
        {
            "name": "index",
            "value": 8142
        },
        {
            "name": "hexID",
            "value": ""
        },
        {
            "name": "oompType",
            "value": "FOOTPRINT"
        },
        {
            "name": "oompSize",
            "value": "kicad"
        },
        {
            "name": "oompColor",
            "value": "kicad-footprints"
        },
        {
            "name": "oompDesc",
            "value": "LED_SMD"
        },
        {
            "name": "oompIndex",
            "value": "LED_RGB_1210"
        },
        {
            "name": "oompName",
            "value": "kicad-footprints/LED_SMD/LED_RGB_1210"
        },
        {
            "name": "kicadDesc",
            "value": "RGB LED 3.2x2.7mm http://www.avagotech.com/docs/AV02-0610EN"
        },
        {
            "name": "kicadTags",
            "value": "LED 3227"
        },
        {
            "name": "kicadAttr",
            "value": "smd"
        },
        {
            "name": "kicad3DModel",
            "value": "${KICAD6_3DMODEL_DIR}/LED_SMD.3dshapes/LED_RGB_1210.wrl"
        },
        {
            "name": "oompID",
            "value": "FOOTPRINT-kicad-kicad-footprints-LED_SMD-LED_RGB_1210"
        },
        {
            "name": "name",
            "value": ""
        }
    ]
}