{
    "index": 32016,
    "tags": [
        {
            "name": "index",
            "value": 32016
        },
        {
            "name": "hexID",
            "value": ""
        },
        {
            "name": "oompType",
            "value": "FOOTPRINT"
        },
        {
            "name": "oompSize",
            "value": "eagle"
        },
        {
            "name": "oompColor",
            "value": "eagle-default"
        },
        {
            "name": "oompDesc",
            "value": "con-thomas-betts"
        },
        {
            "name": "oompIndex",
            "value": "H2R09ST"
        },
        {
            "name": "oompName",
            "value": "eagle-default/con-thomas-betts/H2R09ST"
        },
        {
            "name": "oompID",
            "value": "FOOTPRINT-eagle-eagle-default-con-thomas-betts-H2R09ST"
        },
        {
            "name": "name",
            "value": ""
        }
    ]
}