{
    "index": 22477,
    "tags": [
        {
            "name": "index",
            "value": 22477
        },
        {
            "name": "hexID",
            "value": ""
        },
        {
            "name": "oompType",
            "value": "FOOTPRINT"
        },
        {
            "name": "oompSize",
            "value": "kicad"
        },
        {
            "name": "oompColor",
            "value": "kicad-footprints"
        },
        {
            "name": "oompDesc",
            "value": "LED_SMD"
        },
        {
            "name": "oompIndex",
            "value": "LED_Kingbright_KPBD-3224"
        },
        {
            "name": "oompName",
            "value": "kicad-footprints/LED_SMD/LED_Kingbright_KPBD-3224"
        },
        {
            "name": "kicadDesc",
            "value": "Kingbright, dual LED, red-green, dome lens, 3.2 x 2.4 mm Surface Mount LED Lamp (https://www.kingbright.com/attachments/file/psearch/000/00/00/KPBD-3224SURKCGKC(Ver.20A).pdf)"
        },
        {
            "name": "kicadTags",
            "value": "Kingbright dual LED KPBD-3224"
        },
        {
            "name": "kicadAttr",
            "value": "smd"
        },
        {
            "name": "kicad3DModel",
            "value": "${KICAD6_3DMODEL_DIR}/LED_SMD.3dshapes/LED_Kingbright_KPBD-3224.wrl"
        },
        {
            "name": "oompID",
            "value": "FOOTPRINT-kicad-kicad-footprints-LED_SMD-LED_Kingbright_KPBD-3224"
        },
        {
            "name": "name",
            "value": ""
        }
    ]
}