{
    "index": 354,
    "tags": [
        {
            "name": "index",
            "value": 354
        },
        {
            "name": "hexID",
            "value": ""
        },
        {
            "name": "oompType",
            "value": "FOOTPRINT"
        },
        {
            "name": "oompSize",
            "value": "kicad"
        },
        {
            "name": "oompColor",
            "value": "kicad-footprints"
        },
        {
            "name": "oompDesc",
            "value": "Calibration_Scale"
        },
        {
            "name": "oompIndex",
            "value": "Gauge_10mm_Type5_SilkScreenTop"
        },
        {
            "name": "oompName",
            "value": "kicad-footprints/Calibration_Scale/Gauge_10mm_Type5_SilkScreenTop"
        },
        {
            "name": "kicadDesc",
            "value": "Gauge, Massstab, 10mm, SilkScreenTop, Type 5,"
        },
        {
            "name": "kicadTags",
            "value": "Gauge Massstab 10mm SilkScreenTop Type 5"
        },
        {
            "name": "kicadAttr",
            "value": "exclude_from_pos_files exclude_from_bom"
        },
        {
            "name": "oompID",
            "value": "FOOTPRINT-kicad-kicad-footprints-Calibration_Scale-Gauge_10mm_Type5_SilkScreenTop"
        },
        {
            "name": "name",
            "value": ""
        }
    ]
}