<package name="SOT23W" urn="urn:adsk.eagle:footprint:8085106/1">
<description>&lt;b&gt;SMALL OUTLINE TRANSISTOR&lt;/b&gt;&lt;p&gt;&#xD;
wave soldering</description>
<wire x1="-1.973" y1="1.983" x2="1.973" y2="1.983" width="0.0508" layer="39"/>
<wire x1="1.973" y1="-1.983" x2="-1.973" y2="-1.983" width="0.0508" layer="39"/>
<wire x1="-1.973" y1="-1.983" x2="-1.973" y2="1.983" width="0.0508" layer="39"/>
<wire x1="1.973" y1="1.983" x2="1.973" y2="-1.983" width="0.0508" layer="39"/>
<wire x1="1.422" y1="0.66" x2="1.422" y2="-0.66" width="0.1524" layer="51"/>
<wire x1="1.422" y1="-0.66" x2="-1.422" y2="-0.66" width="0.1524" layer="51"/>
<wire x1="-1.422" y1="-0.66" x2="-1.422" y2="0.66" width="0.1524" layer="51"/>
<wire x1="-1.422" y1="0.66" x2="1.422" y2="0.66" width="0.1524" layer="51"/>
<smd name="3" x="0" y="1.303" dx="1" dy="1.4" layer="1"/>
<smd name="2" x="0.95" y="-1.303" dx="1" dy="1.4" layer="1"/>
<smd name="1" x="-0.95" y="-1.303" dx="1" dy="1.4" layer="1"/>
<text x="-2.03" y="2.0701" size="1.27" layer="25">&gt;NAME</text>
<text x="-1.9949" y="-3.3701" size="1.27" layer="27">&gt;VALUE</text>
<rectangle x1="-0.2286" y1="0.7112" x2="0.2286" y2="1.2954" layer="51"/>
<rectangle x1="0.7112" y1="-1.2954" x2="1.1684" y2="-0.7112" layer="51"/>
<rectangle x1="-1.1684" y1="-1.2954" x2="-0.7112" y2="-0.7112" layer="51"/>
<rectangle x1="-0.5001" y1="-0.5001" x2="0.5001" y2="0.5001" layer="35"/>
</package>
