{
    "index": 7197,
    "tags": [
        {
            "name": "index",
            "value": 7197
        },
        {
            "name": "hexID",
            "value": ""
        },
        {
            "name": "oompType",
            "value": "FOOTPRINT"
        },
        {
            "name": "oompSize",
            "value": "eagle"
        },
        {
            "name": "oompColor",
            "value": "eagle-default"
        },
        {
            "name": "oompDesc",
            "value": "on-semiconductor"
        },
        {
            "name": "oompIndex",
            "value": "SOT-563"
        },
        {
            "name": "oompName",
            "value": "eagle-default/on-semiconductor/SOT-563"
        },
        {
            "name": "oompID",
            "value": "FOOTPRINT-eagle-eagle-default-on-semiconductor-SOT-563"
        },
        {
            "name": "name",
            "value": ""
        }
    ]
}