<package name="WS2812">
<wire x1="-2.5" y1="2.5" x2="2.5" y2="2.5" width="0.127" layer="21"/>
<wire x1="2.5" y1="2.5" x2="2.5" y2="-1.5" width="0.127" layer="21"/>
<wire x1="2.5" y1="-1.5" x2="2.5" y2="-2.5" width="0.127" layer="21"/>
<wire x1="2.5" y1="-2.5" x2="1.5" y2="-2.5" width="0.127" layer="21"/>
<wire x1="1.5" y1="-2.5" x2="-2.5" y2="-2.5" width="0.127" layer="21"/>
<wire x1="-2.5" y1="-2.5" x2="-2.5" y2="2.5" width="0.127" layer="21"/>
<wire x1="1.5" y1="-2.5" x2="2.5" y2="-1.5" width="0.127" layer="21"/>
<circle x="2.934" y="-2.688" radius="0.1414" width="0.127" layer="21"/>
<circle x="0" y="0" radius="2.1" width="0.127" layer="21"/>
<smd name="NC" x="-2" y="1.7" dx="2" dy="1.1" layer="1"/>
<smd name="LEDVDD" x="-2" y="0" dx="2" dy="1.1" layer="1"/>
<smd name="VSS" x="-2" y="-1.7" dx="2" dy="1.1" layer="1"/>
<smd name="DO" x="2" y="-1.7" dx="2" dy="1.1" layer="1"/>
<smd name="DI" x="2" y="0" dx="2" dy="1.1" layer="1"/>
<smd name="VDD" x="2" y="1.7" dx="2" dy="1.1" layer="1"/>
<text x="-1.7" y="2.9" size="1.27" layer="25" font="vector">&gt;NAME</text>
<text x="-2" y="-4.1" size="1.27" layer="27" font="vector">&gt;VALUE</text>
</package>
