{
    "tags": [
        {
            "name": "hexID",
            "value": ""
        },
        {
            "name": "oompType",
            "value": "FOOTPRINT"
        },
        {
            "name": "oompSize",
            "value": "eagle"
        },
        {
            "name": "oompColor",
            "value": "eagle-default"
        },
        {
            "name": "oompDesc",
            "value": "analog-devices"
        },
        {
            "name": "oompIndex",
            "value": "SO-16W"
        },
        {
            "name": "oompName",
            "value": "eagle-default/analog-devices/SO-16W"
        },
        {
            "name": "oompID",
            "value": "FOOTPRINT-eagle-eagle-default-analog-devices-SO-16W"
        },
        {
            "name": "name",
            "value": ""
        }
    ]
}