{
    "index": 14687,
    "tags": [
        {
            "name": "index",
            "value": 14687
        },
        {
            "name": "hexID",
            "value": ""
        },
        {
            "name": "oompType",
            "value": "FOOTPRINT"
        },
        {
            "name": "oompSize",
            "value": "kicad"
        },
        {
            "name": "oompColor",
            "value": "kicad-footprints"
        },
        {
            "name": "oompDesc",
            "value": "Calibration_Scale"
        },
        {
            "name": "oompIndex",
            "value": "Gauge_100mm_Grid_Type1_CopperTop"
        },
        {
            "name": "oompName",
            "value": "kicad-footprints/Calibration_Scale/Gauge_100mm_Grid_Type1_CopperTop"
        },
        {
            "name": "kicadDesc",
            "value": "Gauge, Massstab, 100mm, Gitter, Grid, CopperTop, Type 1,"
        },
        {
            "name": "kicadTags",
            "value": "Gauge Massstab 100mm Gitter Grid CopperTop Type 1"
        },
        {
            "name": "kicadAttr",
            "value": "exclude_from_pos_files exclude_from_bom"
        },
        {
            "name": "oompID",
            "value": "FOOTPRINT-kicad-kicad-footprints-Calibration_Scale-Gauge_100mm_Grid_Type1_CopperTop"
        },
        {
            "name": "name",
            "value": ""
        }
    ]
}