{
    "index": 32366,
    "tags": [
        {
            "name": "index",
            "value": 32366
        },
        {
            "name": "hexID",
            "value": ""
        },
        {
            "name": "oompType",
            "value": "FOOTPRINT"
        },
        {
            "name": "oompSize",
            "value": "eagle"
        },
        {
            "name": "oompColor",
            "value": "eagle-default"
        },
        {
            "name": "oompDesc",
            "value": "con-wago-500"
        },
        {
            "name": "oompIndex",
            "value": "W239-104"
        },
        {
            "name": "oompName",
            "value": "eagle-default/con-wago-500/W239-104"
        },
        {
            "name": "oompID",
            "value": "FOOTPRINT-eagle-eagle-default-con-wago-500-W239-104"
        },
        {
            "name": "name",
            "value": ""
        }
    ]
}