{
    "index": 9069,
    "tags": [
        {
            "name": "index",
            "value": 9069
        },
        {
            "name": "hexID",
            "value": ""
        },
        {
            "name": "oompType",
            "value": "FOOTPRINT"
        },
        {
            "name": "oompSize",
            "value": "kicad"
        },
        {
            "name": "oompColor",
            "value": "kicad-footprints"
        },
        {
            "name": "oompDesc",
            "value": "Package_DFN_QFN"
        },
        {
            "name": "oompIndex",
            "value": "DFN-8-1EP_2x2mm_P0.45mm_EP0.64x1.38mm"
        },
        {
            "name": "oompName",
            "value": "kicad-footprints/Package_DFN_QFN/DFN-8-1EP_2x2mm_P0.45mm_EP0.64x1.38mm"
        },
        {
            "name": "kicadDesc",
            "value": "DC8 Package 8-Lead Plastic DFN (2mm x 2mm) (see Linear Technology DFN_8_05-08-1719.pdf)"
        },
        {
            "name": "kicadTags",
            "value": "DFN 0.45"
        },
        {
            "name": "kicadAttr",
            "value": "smd"
        },
        {
            "name": "kicad3DModel",
            "value": "${KICAD6_3DMODEL_DIR}/Package_DFN_QFN.3dshapes/DFN-8-1EP_2x2mm_P0.45mm_EP0.64x1.38mm.wrl"
        },
        {
            "name": "oompID",
            "value": "FOOTPRINT-kicad-kicad-footprints-Package_DFN_QFN-DFN-8-1EP_2x2mm_P0.45mm_EP0.64x1.38mm"
        },
        {
            "name": "name",
            "value": ""
        }
    ]
}